classic_FindS/__init__.py
classic_FindS-2.0.0.dist-info/LICENSE
classic_FindS-2.0.0.dist-info/METADATA
classic_FindS-2.0.0.dist-info/WHEEL
classic_FindS-2.0.0.dist-info/top_level.txt
classic_FindS-2.0.0.dist-info/RECORD
