Metadata-Version: 2.1
Name: classic-FindS
Version: 2.0.0
Summary: Find-S algorithm is a Machine Learning Algorithm that finds the most specific hypothesis that fits all the positive examples.
Home-page: https://github.com/safir72347/ML-FindS-PyPi
Author: Safir Motiwala
Author-email: safirmotiwala@gmail.com
License: UNKNOWN
Platform: UNKNOWN
Classifier: Programming Language :: Python :: 3
Classifier: License :: OSI Approved :: MIT License
Classifier: Operating System :: OS Independent
Requires-Python: >=3.0
